flowcean/__about__.py
flowcean/__init__.py
flowcean/cli/__init__.py
flowcean/cli/logging.py
flowcean/core/__init__.py
flowcean/core/learner.py
flowcean/core/metric.py
flowcean/core/model.py
flowcean/core/transform.py
flowcean/core/environment/__init__.py
flowcean/core/environment/actable.py
flowcean/core/environment/active.py
flowcean/core/environment/chained.py
flowcean/core/environment/incremental.py
flowcean/core/environment/observable.py
flowcean/core/environment/offline.py
flowcean/core/environment/stepable.py
flowcean/environments/__init__.py
flowcean/environments/csv.py
flowcean/environments/dataset.py
flowcean/environments/hybrid_system.py
flowcean/environments/json.py
flowcean/environments/ode_environment.py
flowcean/environments/parquet.py
flowcean/environments/pytorch.py
flowcean/environments/rosbag.py
flowcean/environments/streaming.py
flowcean/environments/train_test_split.py
flowcean/environments/uri.py
flowcean/environments/yaml.py
flowcean/learners/__init__.py
flowcean/learners/dummy_learner.py
flowcean/learners/lightning.py
flowcean/learners/linear_regression.py
flowcean/learners/regression_tree.py
flowcean/learners/grpc/__init__.py
flowcean/learners/grpc/learner.py
flowcean/learners/grpc/_generated/__init__.py
flowcean/learners/grpc/_generated/learner_pb2.py
flowcean/learners/grpc/_generated/learner_pb2_grpc.py
flowcean/metrics/__init__.py
flowcean/metrics/classification.py
flowcean/metrics/regression.py
flowcean/metrics/report.py
flowcean/models/__init__.py
flowcean/models/pytorch.py
flowcean/models/sklearn.py
flowcean/strategies/__init__.py
flowcean/strategies/active.py
flowcean/strategies/incremental.py
flowcean/strategies/offline.py
flowcean/transforms/__init__.py
flowcean/transforms/explode.py
flowcean/transforms/flatten.py
flowcean/transforms/match_sampling_rate.py
flowcean/transforms/one_hot.py
flowcean/transforms/rechunk.py
flowcean/transforms/rename.py
flowcean/transforms/resample.py
flowcean/transforms/select.py
flowcean-0.2.0.dist-info/METADATA
flowcean-0.2.0.dist-info/WHEEL
flowcean-0.2.0.dist-info/licenses/AUTHORS
flowcean-0.2.0.dist-info/licenses/LICENSE
flowcean-0.2.0.dist-info/RECORD
