Metadata-Version: 2.3
Name: flowcean
Version: 0.2.0
Summary: Automatic generation of models for cyber-physical systems.
Project-URL: Documentation, https://flowcean.me/
Project-URL: Issues, https://github.com/flowcean/flowcean/issues
Project-URL: Source, https://github.com/flowcean/flowcean
Author-email: The AGenC Team <agenc.team@tuhh.de>
Classifier: License :: OSI Approved :: BSD License
Classifier: Operating System :: OS Independent
Classifier: Programming Language :: Python :: 3
Classifier: Programming Language :: Python :: 3.12
Classifier: Topic :: Software Development :: Libraries :: Python Modules
Requires-Python: ~=3.12.7
Requires-Dist: docker>=7.1.0
Requires-Dist: grpcio>=1.67.0
Requires-Dist: joblib>=1.4.2
Requires-Dist: lightning>=2.4.0
Requires-Dist: numpy>=1.26.4
Requires-Dist: polars>=1.9.0
Requires-Dist: protobuf>=5.28.2
Requires-Dist: rosbags-dataframe>=0.10.0
Requires-Dist: rosbags>=0.10.4
Requires-Dist: ruamel-yaml>=0.18.6
Requires-Dist: scikit-learn>=1.5.2
Requires-Dist: scipy>=1.14.1
Requires-Dist: torch>=2.5.0
Requires-Dist: tqdm>=4.66.5
